ptvulns/__init__.py
ptvulns/_version.py
ptvulns/ptvulns.py
ptvulns/3rd_party/cpe_search/LICENSE
ptvulns/3rd_party/cpe_search/README.md
ptvulns/3rd_party/cpe_search/config.json
ptvulns/3rd_party/cpe_search/config_mariadb.json
ptvulns/3rd_party/cpe_search/cpe_search.py
ptvulns/3rd_party/cpe_search/create_sql_statements.json
ptvulns/3rd_party/cpe_search/database_wrapper_functions.py
ptvulns/3rd_party/cpe_search/requirements.txt
ptvulns/3rd_party/cpe_search/__pycache__/database_wrapper_functions.cpython-313.pyc
ptvulns/3rd_party/cve_finder/LICENSE
ptvulns/3rd_party/cve_finder/README.md
ptvulns/3rd_party/cve_finder/__init__.py
ptvulns/3rd_party/cve_finder/__main__.py
ptvulns/3rd_party/cve_finder/config.py
ptvulns/3rd_party/cve_finder/test_cpe.txt
ptvulns/3rd_party/cve_finder/__pycache__/config.cpython-313.pyc
ptvulns/3rd_party/cve_finder/analysis/__init__.py
ptvulns/3rd_party/cve_finder/analysis/data_processing.py
ptvulns/3rd_party/cve_finder/analysis/__pycache__/__init__.cpython-313.pyc
ptvulns/3rd_party/cve_finder/analysis/__pycache__/data_processing.cpython-313.pyc
ptvulns/3rd_party/cve_finder/argument_parser/__init__.py
ptvulns/3rd_party/cve_finder/argument_parser/parser.py
ptvulns/3rd_party/cve_finder/argument_parser/__pycache__/__init__.cpython-313.pyc
ptvulns/3rd_party/cve_finder/argument_parser/__pycache__/parser.cpython-313.pyc
ptvulns/3rd_party/cve_finder/cve_search/__init__.py
ptvulns/3rd_party/cve_finder/cve_search/cve.py
ptvulns/3rd_party/cve_finder/cve_search/request_handler.py
ptvulns/3rd_party/cve_finder/cve_search/__pycache__/__init__.cpython-313.pyc
ptvulns/3rd_party/cve_finder/cve_search/__pycache__/cve.cpython-313.pyc
ptvulns/3rd_party/cve_finder/cve_search/__pycache__/request_handler.cpython-313.pyc
ptvulns/3rd_party/cve_finder/normalizer/__init__.py
ptvulns/3rd_party/cve_finder/normalizer/normalizer.py
ptvulns/3rd_party/cve_finder/normalizer/__pycache__/__init__.cpython-313.pyc
ptvulns-0.0.7.dist-info/licenses/LICENSE
ptvulns-0.0.7.dist-info/METADATA
ptvulns-0.0.7.dist-info/WHEEL
ptvulns-0.0.7.dist-info/entry_points.txt
ptvulns-0.0.7.dist-info/top_level.txt
ptvulns-0.0.7.dist-info/RECORD
